nullsafe/__init__.py
nullsafe/core.py
test/__init__.py
test/test_cases.py
nullsafe-0.2.1.dist-info/LICENSE
nullsafe-0.2.1.dist-info/METADATA
nullsafe-0.2.1.dist-info/WHEEL
nullsafe-0.2.1.dist-info/top_level.txt
nullsafe-0.2.1.dist-info/zip-safe
nullsafe-0.2.1.dist-info/RECORD
