Metadata-Version: 2.1
Name: nullsafe
Version: 0.2.1
Summary: Null safe support for Python
Home-page: https://github.com/paaksing/nullsafe-python
Author: Paaksing
Author-email: paaksingtech@gmail.com
License: MIT
Keywords: null-safe,nullsafe,none aware,python
Platform: UNKNOWN
Classifier: Development Status :: 5 - Production/Stable
Classifier: Programming Language :: Python :: 3.7
Classifier: Environment :: Plugins
Classifier: Intended Audience :: Developers
Classifier: License :: OSI Approved :: MIT License
Classifier: Natural Language :: English
Classifier: Operating System :: OS Independent
Classifier: Topic :: Software Development :: Libraries :: Python Modules
Classifier: Topic :: Utilities
Classifier: Typing :: Typed
License-File: LICENSE
